origin/__init__.py
origin/listners.py
origin/packets.py
origin/peer.py
origin/node/__init__.py
origin/node/client.py
origin/node/generic.py
origin/node/server.py
pyorigin-0.0.1.dist-info/METADATA
pyorigin-0.0.1.dist-info/WHEEL
pyorigin-0.0.1.dist-info/top_level.txt
pyorigin-0.0.1.dist-info/RECORD
